mpl_volume_viewer.py
mpl_volume_viewer-0.1.0.dist-info/LICENSE
mpl_volume_viewer-0.1.0.dist-info/METADATA
mpl_volume_viewer-0.1.0.dist-info/WHEEL
mpl_volume_viewer-0.1.0.dist-info/top_level.txt
mpl_volume_viewer-0.1.0.dist-info/zip-safe
mpl_volume_viewer-0.1.0.dist-info/RECORD
