Metadata-Version: 2.1
Name: mpl-volume-viewer
Version: 0.1.0
Summary: matplotlib orthoslice volume viewer in Python
Home-page: https://github.com/jni/mpl-volume-viewer
Author: Juan Nunez-Iglesias
Author-email: juan.nunez-iglesias@monash.edu
License: BSD 3-Clause
Download-URL: https://github.com/jni/mpl-volume-viewer
Platform: UNKNOWN
Classifier: Development Status :: 2 - Pre-Alpha
Classifier: Intended Audience :: Education
Classifier: Intended Audience :: Science/Research
Classifier: License :: OSI Approved :: BSD License
Classifier: Programming Language :: Python
Classifier: Programming Language :: Python :: 3 :: Only
Classifier: Programming Language :: Python :: 3.6
Classifier: Programming Language :: Python :: 3.7
Classifier: Programming Language :: Python :: 3.8
Classifier: Topic :: Scientific/Engineering
Classifier: Topic :: Scientific/Engineering :: Visualization
Classifier: Topic :: Scientific/Engineering :: Information Analysis
Classifier: Topic :: Scientific/Engineering :: Bio-Informatics
Classifier: Topic :: Utilities
Classifier: Operating System :: Microsoft :: Windows
Classifier: Operating System :: POSIX
Classifier: Operating System :: Unix
Classifier: Operating System :: MacOS
Classifier: Framework :: Matplotlib
Requires-Python: >=3.6
Requires-Dist: matplotlib (>=3.0)
Requires-Dist: numpy (>=1.16.0)
